[
    {
        "id":0,
        "namaProduct":"INBook X1 | Core i3-1005G1",
        "brand":"Infinix",
        "tahunRilis":"2021",
        "prosesor":"Core i3 1005G1",
        "penyimpanan":"256 GB SSD",
        "ram":"8 GB",
        "ukuranLayar":"14 inch",
        "harga":"Rp 5.234.000",
        "image":"96202_LL_1.jpg"
    },
    {
        "id":1,
        "namaProduct":"IdeaPad Slim 3 | Ryzen 3-5300U",
        "brand":"Lenovo",
        "tahunRilis":"2021",
        "prosesor":"Ryzen 3",
        "penyimpanan":"512 GB SSD",
        "ram":"8 GB",
        "ukuranLayar":"14 inch",
        "harga":"Rp 8.000.000",
        "image":"97662_LL_1.jpg"
    },
    {
        "id":2,
        "namaProduct":"ThinkPad T410",
        "brand":"Lenovo",
        "tahunRilis":"2009",
        "prosesor":"Core i5 520M",
        "penyimpanan":"320 GB HDD",
        "ram":"4 GB",
        "ukuranLayar":"14 inch",
        "harga":"Rp 2.499.000",
        "image":"1419_LL_1.jpg"
    },
    {
        "id":3,
        "namaProduct":"Legion 5",
        "brand":"Lenovo",
        "tahunRilis":"2020",
        "prosesor":"Ryzen 7 4800H",
        "penyimpanan":"1 TB SSD",
        "ram":"32 GB",
        "ukuranLayar":"15.6 inch",
        "harga":"Rp 12.099.000",
        "image":"92838_LL_1.jpg"
    },
    {
        "id":4,
        "namaProduct":"14s-dk1524AU",
        "brand":"HP",
        "tahunRilis":"2018",
        "prosesor":"Athlon Gold 3050U",
        "penyimpanan":"512 GB SSD",
        "ram":"4 GB",
        "ukuranLayar":"14 inch",
        "harga":"Rp 4.645.000",
        "image":"97621_LL_1.jpg"
    },
    {
        "id":5,
        "namaProduct":"BR1100FKA-BP0410T",
        "brand":"ASUS",
        "tahunRilis":"2019",
        "prosesor":"Celeron N4500",
        "penyimpanan":"128 GB eMMC",
        "ram":"4 GB",
        "ukuranLayar":"11.6 inch",
        "harga":"Rp 3.286.000",
        "image":"96169_LL_1.jpg"
    },
    {
        "id":6,
        "namaProduct":"V14-ADA-ETID",
        "brand":"Lenovo",
        "tahunRilis":"2019",
        "prosesor":"Athlon 3020E",
        "penyimpanan":"256 GB SSD",
        "ram":"8 GB",
        "ukuranLayar":"14 inch",
        "harga":"Rp 3.849.000",
        "image":"95990_LL_1.jpg"
    },
    {
        "id":7,
        "namaProduct":"Legion Y520-7BID",
        "brand":"Lenovo",
        "tahunRilis":"2017",
        "prosesor":"Core i7 7700HQ",
        "penyimpanan":"1 TB HDD 256 GB SSD",
        "ram":"8 GB",
        "ukuranLayar":"15.6 inch",
        "harga":"Rp 5.116.500",
        "image":"76009_LL_1.jpg"
    },
    {
        "id":8,
        "namaProduct":"Nitro 5 AN515-52-51T2",
        "brand":"Acer",
        "tahunRilis":"2018",
        "prosesor":"Core i5 Core™ i5-8300H",
        "penyimpanan":"1 TB HDD",
        "ram":"8 GB",
        "ukuranLayar":"15.6 inch",
        "harga":"Rp 9.345.000",
        "image":"81610_LL_1.jpg"
    },
    {
        "id":9,
        "namaProduct":"RedmiBook 15",
        "brand":"Xiaomi",
        "tahunRilis":"2022",
        "prosesor":"Core i3 1115G4",
        "penyimpanan":"256 GB SSD",
        "ram":"8 GB",
        "ukuranLayar":"15.6 inch",
        "harga":"Rp 6.099.000",
        "image":"96413_LL_1.jpg"
    },
    {
        "id":10,
        "namaProduct":"Nitro 5 AN515-56-5603",
        "brand":"Acer",
        "tahunRilis":"2021",
        "prosesor":"Core i5 11300H",
        "penyimpanan":"512 GB SSD",
        "ram":"8 GB",
        "ukuranLayar":"15.6 inch",
        "harga":"Rp 12.125.000",
        "image":"95896_LL_1.jpg"
    },
    {
        "id":11,
        "namaProduct":"Zenbook 14 UX435EG-AI511NP",
        "brand":"ASUS",
        "tahunRilis":"2020",
        "prosesor":"Core i5 1135G7",
        "penyimpanan":"512 GB SSD",
        "ram":"8 GB",
        "ukuranLayar":"14 inch",
        "harga":"Rp 14.649.000",
        "image":"96220_LL_1.jpg"
    }
]